<?xml version="1.0" ?><annotation verified="no"><source><database>Unknown</database></source><object><bndbox><xmin>189</xmin><ymin>54</ymin><ymax>663</ymax><xmax>471</xmax></bndbox><difficult>0</difficult><pose>Unspecified</pose><name>luggage</name><truncated>0</truncated></object><segmented>0</segmented><path>/usr/local/machine_learning/pycharm_workspace/yinerche_detector/Annotations/NewTechnology326.xml</path><folder>JPEGImages</folder><size><width>950</width><depth>3</depth><height>695</height></size><filename>NewTechnology326</filename></annotation>