<?xml version="1.0" ?><annotation verified="no"><source><database>Unknown</database></source><object><bndbox><xmin>92</xmin><ymin>33</ymin><ymax>937</ymax><xmax>839</xmax></bndbox><difficult>0</difficult><pose>Unspecified</pose><name>pram</name><truncated>0</truncated></object><segmented>0</segmented><path>/usr/local/machine_learning/pycharm_workspace/yinerche_detector/Annotations/NewTechnology295.xml</path><folder>JPEGImages</folder><size><width>864</width><depth>3</depth><height>1000</height></size><filename>NewTechnology295</filename></annotation>